yarea/__init__.py
yarea/data/__init__.py
yarea/data/default_pyradiomics.yaml
yarea/feature_extraction.py
yarea/image_processing.py
yarea/loaders.py
yarea/metadata.py
yarea/negative_controls.py
yarea/pipeline.py
yarea-0.6.0.dist-info/LICENSE
yarea-0.6.0.dist-info/METADATA
yarea-0.6.0.dist-info/WHEEL
yarea-0.6.0.dist-info/entry_points.txt
yarea-0.6.0.dist-info/RECORD
