Metadata-Version: 2.1
Name: yarea
Version: 0.6.0
Summary: A package to extract radiomic features!
License: MIT
Author: Katy Scott
Requires-Python: >=3.9,<4
Classifier: License :: OSI Approved :: MIT License
Classifier: Programming Language :: Python :: 3
Classifier: Programming Language :: Python :: 3.9
Classifier: Programming Language :: Python :: 3.10
Classifier: Programming Language :: Python :: 3.11
Classifier: Programming Language :: Python :: 3.12
Requires-Dist: dicom-parser (>=1.2.3)
Requires-Dist: matplotlib (>=3.8.2)
Requires-Dist: med-imagetools (>=1.1.6,<2.0.0)
Requires-Dist: pydicom (>=2.3.1)
Requires-Dist: pyradiomics (>=3.1.0,<4.0.0)
Requires-Dist: simpleitk (>=2.3.1)
